{"nVO9dq/dRQw1RMgjzhhTHw==":"mbr-121x181.jpg","mC+Ei6tGxTFcnRZvY8bRUw==":"ross_tanned-615x409.png","QjxzUp2NW3bTWerzhy4njw==":"ross-800x406.jpg","hME2zaEhZ2GEWpur0ygSsA==":"mbr-400x266.jpg","hofF70QMgyBKIwuqp80hKQ==":"mbr-400x266.jpeg","Sbbmc2YkNE3pqJMqKJlWxw==":"nepalpalace-280x122.jpg","Mn4hIUtjwh1AUczWQlKkRQ==":"nepalpalace-1600x700.jpeg","pREvaANylwQyClIaLu/5TQ==":"nepalpalace-1-1600x700.jpeg","AEQyX58StV5hJ7sYfdtMfA==":"nepalpalace_border-1-1600x792.png","fzsaiGlaCu7P6Fcahfy1Qg==":"dsc-8712.jpeg","Sz5tfQaqRyY0ZLA7jedcLw==":"mmf-banner.jpg","FN8o6NukGBTrV87h30ODIA==":"output-onlinejpgtools-98x112.png","ZX3fnHu6LvdZEwKbPcZR8g==":"mbr-1920x1920.jpg","x/wscO8hEzB1CYJbfvUPIA==":"mbr-1-1920x1080.png","xTG0lk9ulLb/Ua5Okm2rPA==":"mbr-2-1920x1280.jpg","ad4kl1EYGmjUWfcegohdjA==":"03-padwa000-2-815x1555.png","BCYEMuTELq9A34sNurPzpQ==":"dsc-8792-816x629.jpeg","oMcV7uwlXrdmqtAC7QFqbQ==":"05-mmfnewsletter07-2-501x707.png","BENbeQ9BB4NRD1G7VQ9pUw==":"background5-1.jpeg","K/YAS5dgVXLTKrJKo1WH8Q==":"mbr-1920x1280.jpeg","pHEYrht8diDTRv1SyrNWJg==":"02-mejwani03-2800x2190.jpg","JVp6NX/VN6EikilrqsGC7g==":"06-indiaday09-1-748x615.jpeg","sPfRvQzuXXFDC5gDU9C0dg==":"dsc-8726-5700x3900.jpeg","YDtZihYQpfEIHpeM/AFhhA==":"03-padwa02-1-3600x2400.jpeg","F2kxTyHcuog6+4By7anyyw==":"dsc-8773-6000x3539.jpeg","I8Wmx7J4KcTMkmWzeFrRFg==":"06-indiaday02-777x598.jpeg","e8KYrh999Nm37JIU+1dA1Q==":"dsc-8783-2326x1862.jpeg","QZNWpNUUCrdF2jsQKUo1fw==":"06-indiaday05-2326x1984.jpeg","BFLswgBXYGfbo9+jhLY1og==":"img-632-2326x1748.jpeg","7acrFn6M6dPUQmOBmEIw9A==":"img-656-2326x1999.jpeg","d61LqE2l8UphUTIUZzPgRA==":"03-padwa31-2326x4142.jpeg","Q0FFa/TzQDzHwWkxBX4a1w==":"03-padwa40-2326x3489.jpeg","D+HkZXg9Pto57igpahoEGQ==":"04-kilbil01-1024x768.jpeg","xIQZ3jzmj2+Acw5GJ4BT8A==":"mbr-1920x1920.png","0/rm7PD6bnyWoL7ga1lBwA==":"03-padwa14-2-2326x2400.jpeg","HHSbLiG4e8lVYfP0oeUaIg==":"mbr-1-1920x1280.jpeg","9wAS0ZM/KZ5vkSxAKPfcdQ==":"mbr-1-1920x1278.jpeg","glj42ugrD+nbFjygJpdMdg==":"06-indiaday05-1-2326x1984.jpeg","0kHjHkxIfjDc9PWWBrsC3A==":"dsc-8743-2326x1745.jpeg","RY8Tt5Y6HaHqRCK2AlwcXw==":"img-1082-1536x2046.jpg","WiLVwtToU4r+cUYdUOI/uA==":"mbr-4-1920x1280.jpeg","liIdGkbU4Of/yDyJ9EJ9tQ==":"06-indiaday05-2-2326x1984.jpeg","VgfngALmCcE6O7y+cXRaNA==":"images-225x225.png","R/RkY6blh0Lb7hbHMQXmuA==":"padmajammf-596x633.jpeg","M+OhaeIpvDMEWNdTAhm0+g==":"img_1082zfd-1-596x596.png","qVzy3O1Z4nMHCToHMYJDvA==":"padmajammf-1-596x633.jpeg","r8A1YbHndRxlKHgw3dViuQ==":"padmajammf-2-596x633.jpeg","m/Su3HUeLOizMsu9sWH6zA==":"mbr-596x397.png","+GCWAaO3VVWyLCWnqPf/Fg==":"mbr-596x596.jpeg","rbWl2/nnLs6py2dEjvsBpg==":"mbr-1-596x596.jpeg","furSjJ25W4z8bA8cgy3tdg==":"mbr-2-596x596.jpeg","VxV6fC3ewwskFskECAs3AA==":"mbr-1478x1920.jpeg","zkj9Id1hv/w3I3cw8uTnfA==":"mbr-2-1920x1080.png","rj/D0Eg/a8omub5GDWhZKA==":"mbr-1-1478x1920.jpeg","WSS1dSK+G4iD5ocFRegNvw==":"mbr-1920x960.png","vZjgL9UHkCJeNalU1tUYYQ==":"mbr-1920x1280.png","EAW3gdrsQRo8oHaYi99j7g==":"mbr-1-1920x1280.png","heHlUVzRrwYA2i6aXLk77g==":"mbr-1920x1372.jpeg","l61OkUZb7QLi36UlNb9Xiw==":"mbr-1-1920x1372.jpeg","E5KArwCc78Yz1ZRbOBBoOA==":"mbr-2-1920x1372.jpeg","81qoua86p2nyHveX82G67w==":"ankush-596x629.jpg","2bSiVB33y9jTN76qYoEc2w==":"ankush-596x629.jpeg","GNEoBfBINywkwm5j059y/g==":"rucha-596x630.jpeg","6+JCpIYsAY0QuL+0SA6mZg==":"bapurao-596x596.jpeg","TZgyJSgj7PQUXoQTNLJ2VA==":"whatsapp%20image%202023-01-31%20at%2010.22.06%20pm-596x596.jpeg"}